odoo/addons/pos_event_sale/README.rst
odoo/addons/pos_event_sale/__init__.py
odoo/addons/pos_event_sale/__manifest__.py
odoo/addons/pos_event_sale/hooks.py
odoo/addons/pos_event_sale/i18n/es.po
odoo/addons/pos_event_sale/i18n/fr.po
odoo/addons/pos_event_sale/i18n/it.po
odoo/addons/pos_event_sale/i18n/pos_event_sale.pot
odoo/addons/pos_event_sale/models/__init__.py
odoo/addons/pos_event_sale/models/event_event.py
odoo/addons/pos_event_sale/models/event_registration.py
odoo/addons/pos_event_sale/models/event_ticket.py
odoo/addons/pos_event_sale/models/pos_config.py
odoo/addons/pos_event_sale/models/pos_order.py
odoo/addons/pos_event_sale/models/pos_order_line.py
odoo/addons/pos_event_sale/readme/CONFIGURE.rst
odoo/addons/pos_event_sale/readme/CONTRIBUTORS.rst
odoo/addons/pos_event_sale/readme/DESCRIPTION.rst
odoo/addons/pos_event_sale/readme/ROADMAP.rst
odoo/addons/pos_event_sale/readme/USAGE.rst
odoo/addons/pos_event_sale/reports/__init__.py
odoo/addons/pos_event_sale/reports/report_pos_order.py
odoo/addons/pos_event_sale/reports/report_pos_order.xml
odoo/addons/pos_event_sale/security/security.xml
odoo/addons/pos_event_sale/static/description/add_event_button.png
odoo/addons/pos_event_sale/static/description/event_calendar.png
odoo/addons/pos_event_sale/static/description/icon.png
odoo/addons/pos_event_sale/static/description/index.html
odoo/addons/pos_event_sale/static/description/ticket_selector.png
odoo/addons/pos_event_sale/static/src/js/db.js
odoo/addons/pos_event_sale/static/src/js/models.js
odoo/addons/pos_event_sale/static/src/js/utils.js
odoo/addons/pos_event_sale/static/src/js/ControlButtons/AddEventButton.js
odoo/addons/pos_event_sale/static/src/js/Popups/EventAvailabilityBadge.js
odoo/addons/pos_event_sale/static/src/js/Popups/EventSelectorPopup/EventCalendar.js
odoo/addons/pos_event_sale/static/src/js/Popups/EventSelectorPopup/EventFilters.js
odoo/addons/pos_event_sale/static/src/js/Popups/EventSelectorPopup/EventItem.js
odoo_addon_pos_event_sale-15.0.3.1.0.7.dist-info/METADATA
odoo_addon_pos_event_sale-15.0.3.1.0.7.dist-info/WHEEL
odoo_addon_pos_event_sale-15.0.3.1.0.7.dist-info/top_level.txt
odoo_addon_pos_event_sale-15.0.3.1.0.7.dist-info/RECORD
